<Patch>
    <Operation Class="PatchOperationConditional">
        <xpath>Defs/StatDef[defName="RangedWeapon_Cooldown"]/parts</xpath>
        <nomatch Class="PatchOperationAdd">
            <xpath>Defs/StatDef[defName="RangedWeapon_Cooldown"]</xpath>
            <value>
                <parts>
                    <li Class="VFECore.Misc.StatPart_Ammo" />
                </parts>
            </value>
        </nomatch>
        <match Class="PatchOperationAdd">
            <xpath>Defs/StatDef[defName="RangedWeapon_Cooldown"]/parts</xpath>
            <value>
                <li Class="VFECore.Misc.StatPart_Ammo" />
            </value>
        </match>
    </Operation>
</Patch>